{
  "label": "exp83_force_steering_guidance_v3_seed42_point_yneg0p1_yaw0",
  "checkpoint": "/home/uniubi/projects/forklift_sim/IsaacLab/logs/rsl_rl/forklift_pallet_insert_lift/2026-03-30_17-35-14_exp83_force_steering_guidance_v3_resume_from_v1_seed42_iter30_256cam/model_29.pt",
  "x_root": -3.5,
  "y_m": -0.1,
  "yaw_deg": 0.0,
  "seed": 20260330,
  "png": "/home/uniubi/projects/forklift_sim/outputs/exp83_single_point_steer_diag/exp83_force_steering_guidance_v3_seed42_point_yneg0p1_yaw0_normal_vs_zero_steer.png",
  "actor_obs_probe_keys": [
    "TensorDict"
  ],
  "actor_policy_value_type": "TensorDict",
  "camera_enabled": true,
  "actor_proprio_dim": 12,
  "actor_proprio_fields": [
    "v_x_r",
    "v_y_r",
    "yaw_rate",
    "lift_pos",
    "lift_vel",
    "prev_drive",
    "prev_steer",
    "prev_lift",
    "y_err_obs",
    "yaw_err_obs",
    "d_traj_signed_obs",
    "yaw_traj_err_obs"
  ],
  "critic_privileged_dim": 15,
  "note": "With camera-enabled policy obs, actor uses image + proprio; inspect actor_proprio_fields for whether signed alignment is present.",
  "modes": {
    "normal": {
      "mode": "normal",
      "csv_path": "/home/uniubi/projects/forklift_sim/outputs/exp83_single_point_steer_diag/exp83_force_steering_guidance_v3_seed42_point_yneg0p1_yaw0_normal_steps.csv",
      "episode_steps": 1070,
      "done": true,
      "success": false,
      "ever_inserted": false,
      "ever_hold_entry": false,
      "ever_clean_insert_ready": false,
      "ever_dirty_insert": false,
      "timeout_like": false,
      "initial_center_y_signed_m": -0.10000000149011612,
      "final_center_y_signed_m": 0.6569629907608032,
      "initial_yaw_err_signed_deg": 0.0,
      "final_yaw_err_signed_deg": -176.9894215473548,
      "initial_d_traj_m": 0.0,
      "final_d_traj_m": 7.865428447723389,
      "min_dist_front_m": 0.03194689750671387,
      "min_d_traj_m": 0.0,
      "max_pallet_disp_xy_m": 3.122422695159912,
      "max_hold_counter": 0.0,
      "mean_abs_raw_steer": 0.33578501081912315,
      "mean_abs_applied_steer": 0.33578501081912315,
      "mean_abs_joint_steer_rad": 0.20953796871145752,
      "mean_abs_steer_tracking_err_rad": 0.010799438164473697,
      "max_abs_raw_steer": 0.34572023153305054,
      "max_abs_applied_steer": 0.34572023153305054,
      "max_abs_joint_steer_rad": 0.22450728714466095,
      "mean_steer_target_cmd": -0.5761099729025475,
      "mean_abs_steer_target_cmd": 0.5761099729025475,
      "mean_steer_guidance_gate": 0.5537999787898821,
      "mean_steer_enforce_gate": 0.2538380723960141,
      "mean_steer_penalty_gate": 0.149902315355759,
      "mean_steer_match": 0.10657895151699814,
      "mean_steer_shortfall": 0.8934210484272965,
      "steer_wrong_sign_frac": 1.0,
      "first_abs_raw_steer_gt_0p1_step": 1,
      "first_insert_step": -1,
      "first_hold_step": -1,
      "first_success_step": -1
    },
    "zero_steer": {
      "mode": "zero_steer",
      "csv_path": "/home/uniubi/projects/forklift_sim/outputs/exp83_single_point_steer_diag/exp83_force_steering_guidance_v3_seed42_point_yneg0p1_yaw0_zero_steer_steps.csv",
      "episode_steps": 1079,
      "done": true,
      "success": false,
      "ever_inserted": true,
      "ever_hold_entry": false,
      "ever_clean_insert_ready": false,
      "ever_dirty_insert": true,
      "timeout_like": false,
      "initial_center_y_signed_m": -0.10000000149011612,
      "final_center_y_signed_m": 0.003907650709152222,
      "initial_yaw_err_signed_deg": 0.0,
      "final_yaw_err_signed_deg": -10.549347555168815,
      "initial_d_traj_m": 0.0,
      "final_d_traj_m": 0.8104631304740906,
      "min_dist_front_m": 0.0,
      "min_d_traj_m": 0.0,
      "max_pallet_disp_xy_m": 0.4762819707393646,
      "max_hold_counter": 0.0,
      "mean_abs_raw_steer": 0.2735150880952805,
      "mean_abs_applied_steer": 0.0,
      "mean_abs_joint_steer_rad": 0.0014584831725719415,
      "mean_abs_steer_tracking_err_rad": 0.0014584831725719415,
      "max_abs_raw_steer": 0.30191296339035034,
      "max_abs_applied_steer": 0.0,
      "max_abs_joint_steer_rad": 0.0033706389367580414,
      "mean_steer_target_cmd": -0.36061052042745795,
      "mean_abs_steer_target_cmd": 0.36061052042745795,
      "mean_steer_guidance_gate": 0.32695844291171633,
      "mean_steer_enforce_gate": 0.965011570088227,
      "mean_steer_penalty_gate": 0.3207194475779453,
      "mean_steer_match": 0.3658743923852795,
      "mean_steer_shortfall": 0.6341256076147205,
      "steer_wrong_sign_frac": 1.0,
      "first_abs_raw_steer_gt_0p1_step": 1,
      "first_insert_step": 224,
      "first_hold_step": -1,
      "first_success_step": -1
    }
  }
}